GPUDashboard.py
runGPUDashboard.py
GPUDashboard-0.2.4.dist-info/METADATA
GPUDashboard-0.2.4.dist-info/RECORD
GPUDashboard-0.2.4.dist-info/WHEEL
GPUDashboard-0.2.4.dist-info/entry_points.txt
GPUDashboard-0.2.4.dist-info/top_level.txt
