Metadata-Version: 2.1
Name: GPUDashboard
Version: 0.2.4
Summary: A NVIDIA GPU dashboard
Home-page: https://github.com/Yuan-Yu/GPUDashboard
Author: YuanYu
Author-email: tearsgundam@gmail.com
License: UNKNOWN
Project-URL: Demo, https://yuan-yu.github.io/GPUDashboard/
Project-URL: Bug Reports, https://github.com/Yuan-Yu/GPUDashboard/issues
Project-URL: Source, https://github.com/Yuan-Yu/GPUDashboard
Keywords: GPU Dashboard
Platform: UNKNOWN
Classifier: Development Status :: 4 - Beta
Classifier: License :: OSI Approved :: MIT License
Classifier: Programming Language :: Python :: 2.7
Classifier: Programming Language :: Python :: 3.6
Requires-Dist: requests
Requires-Dist: datetime
